[{
  "_id": {
    "$oid": "664ca9926d7322e963c55fd0"
  },
  "nombre": "Erikue S.A. de C.V. Oaxaca",
  "direccion": "Calle Geranio 9",
  "rfc": "RAPE120177",
  "telefono": "9531071388",
  "responsable": "Erik Ramos",
  "createdAt": {
    "$date": "2024-05-21T14:02:58.848Z"
  },
  "updatedAt": {
    "$date": "2024-05-21T14:02:58.848Z"
  },
  "__v": 0,
  "ciudad": "Oaxaca"
},
{
  "_id": {
    "$oid": "664cba91e399ad8c137a91ce"
  },
  "nombre": "German S.A. de C.V. Puebla",
  "direccion": "Calle Geranio 9",
  "rfc": "RAPE120177",
  "telefono": "9531071388",
  "responsable": "Erik Ramos",
  "createdAt": {
    "$date": "2024-05-21T15:15:29.065Z"
  },
  "updatedAt": {
    "$date": "2024-05-21T15:15:29.065Z"
  },
  "__v": 0,
  "ciudad": "Puebla"
}]